Workbook
Name Price_Cap: #REF!

Sheet Planning Parameters
A1: 2028/2029 RPM Base Residual Auction Planning Parameters | D1: 46230
B3: RTO | C3: Notes:
A4: Installed Reserve Margin (IRM) | B4: 0.2 | C4: endorsed at the February 19, 2026 MRC meeting. See:https://www.pjm.com/-/media/DotCom/committees-groups/committees/mrc/2026/20260219/20260219-item-01---1-2028-2029-bra-fpr--irm---presentation.pdf
A5: Pool-Wide Accredited UCAP Factor | B5: 0.7834 | C5: endorsed at the February 19, 2026 MRC meeting.
A6: Reference Resource AUCAP Factor | B6: 0.79
A7: Forecast Pool Requirement (FPR) | B7: 0.9401 | C7: endorsed at the February 19, 2026 MRC meeting.
A8: Preliminary Forecast Peak Load | B8: 165953.5 | C8: 2026 Load Report with adjustments for load served outside PJM.
A9: Price Cap ($/MW-ICAP) | B9: 256.75 | C9: Established in ER26-1556
A10: Price Floor ($/MW-ICAP) | B10: 138.25 | C10: Established in ER26-1556
C11: Locational Deliverability Area
B12: RTO | C12: MAAC | D12: EMAAC | E12: SWMAAC | F12: PS | G12: PS NORTH | H12: DPL SOUTH | I12: PEPCO | J12: ATSI | K12: ATSI-Cleveland | L12: COMED | M12: BGE | N12: PL | O12: DAYTON | P12: DEOK | Q12: DOM | R12: JCPL
A13: CETO | B13: NA | C13: -187 | D13: 5903 | E13: 6131 | F13: 6481 | G13: 2712 | H13: 1654 | I13: 3888 | J13: 3910 | K13: 3534 | L13: 1267 | M13: 4568 | N13: 1187 | O13: 2785 | P13: 2800 | Q13: 7758 | R13: 3628
A14: CETL | B14: NA | C14: 1318 | D14: 6904 | E14: 5862 | F14: 8873 | G14: 4656 | H14: 2005 | I14: 5770 | J14: 11803 | K14: 5430 | L14: 1586 | M14: 5658 | N14: 5312 | O14: 4432 | P14: 5934 | Q14: 5992 | R14: 5312
A15: Reliability Requirement | B15: =B8*B7 -> 156012.89 | C15: 54479.4 | D15: 31225.9 | E15: 13327 | F15: 10851.1 | G15: 5230.7 | H15: 2683.9 | I15: 6488.6 | J15: 12544.3 | K15: 5212 | L15: 22817.2 | M15: 6991.2 | N15: 10155 | O15: 3792.1 | P15: 5661.1 | Q15: 30015.5 | R15: 6258.2
A16: Total Peak Load of FRR Entities | B16: =J51 -> 11556 | C16: =J79 -> 0 | D16: =J76 -> 0 | E16: =J77 -> 0 | F16: =J73 -> 0 | G16: =J74 -> 0 | H16: =J64 -> 0 | I16: =J71 -> 0 | J16: =J55 -> 0 | K16: =J56 -> 0 | L16: =J58 -> 0 | M16: =J57 -> 0 | N16: =J72 -> 0 | O16: =J59 -> 0 | P16: =J60 -> 0 | Q16: =J62 -> 0 | R16: =J66 -> 0
A17: Preliminary FRR Obligation | B17: =ROUND(B16*$B$7,1) -> 10863.8 | C17: =ROUND(C16*$B$7,1) -> 0 | D17: =ROUND(D16*$B$7,1) -> 0 | E17: =ROUND(E16*$B$7,1) -> 0 | F17: =ROUND(F16*$B$7,1) -> 0 | G17: =ROUND(G16*$B$7,1) -> 0 | H17: =ROUND(H16*$B$7,1) -> 0 | I17: =ROUND(I16*$B$7,1) -> 0 | ... R17: =ROUND(R16*$B$7,1) -> 0
A18: Reliability Requirement adjusted for FRR | B18: =B15-B17 -> 145149.09 | C18: =C15-C17*C46 -> 54479.4 | D18: =D15-D17*D46 -> 31225.9 | E18: =E15-E17*E46 -> 13327 | F18: =F15-F17 -> 10851.1 | G18: =G15-G17 -> 5230.7 | H18: =H15-H17 -> 2683.9 | I18: =I15-I17 -> 6488.6 | J18: =J15-J17 -> 12544.3 | K18: =K15-K17 -> 5212 | L18: =L15-L17 -> 22817.2 | M18: =M15-M17*M46 -> 6991.2 | N18: =N15-N17 -> 10155 | O18: =O15-O17 -> 3792.1 | P18: =P15-P17 -> 5661.1 | Q18: =Q15-Q17*Q46 -> 30015.5 | R18: =R15-R17 -> 6258.2
A19: Gross CONE, $/MW-Day (UCAP Price) | B19: ='Net CONE'!E41 -> 776.14 | C19: ='Net CONE'!E28 -> 756.66 | D19: ='Net CONE'!E19 -> 756.03 | E19: ='Net CONE'!E23 -> 769.9 | F19: ='Net CONE'!E17 -> 756.03 | G19: ='Net CONE'!E17 -> 756.03 | H19: ='Net CONE'!E14 -> 756.03 | I19: ='Net CONE'!E22 -> 769.9 | J19: ='Net CONE'!E32 -> 745.62 | K19: ='Net CONE'!E32 -> 745.62 | L19: ='Net CONE'!E40 -> 860.07 | M19: ='Net CONE'!E21 -> 769.9 | N19: ='Net CONE'!E27 -> 749.09 | O19: ='Net CONE'!E33 -> 745.62 | P19: ='Net CONE'!E34 -> 745.62 | Q19: ='Net CONE'!E36 -> 745.62 | R19: ='Net CONE'!E15 -> 756.03
A20: E&AS Value, $/MW-Day (UCAP Price) | B20: =_xlfn.XLOOKUP(B12,'Net CONE'!$A$12:$A$41,'Net CONE'!$G$12:$G$41,0)/(DATE(LEFT($A$1,4)*1+1,5,31)-(DATE(LEFT($A$1,4)*1,6,1))+1) -> 450.4481 | C20: =_xlfn.XLOOKUP(C12,'Net CONE'!$A$12:$A$41,'Net CONE'!$G$12:$G$41,0)/(DATE(LEFT($A$1,4)*1+1,5,31)-(DATE(LEFT($A$1,4)*1,6,1))+1) -> 327.02152 | D20: =_xlfn.XLOOKUP(D12,'Net CONE'!$A$12:$A$41,'Net CONE'!$G$12:$G$41,0)/(DATE(LEFT($A$1,4)*1+1,5,31)-(DATE(LEFT($A$1,4)*1,6,1))+1) -> 214.27152 | E20: =_xlfn.XLOOKUP(E12,'Net CONE'!$A$12:$A$41,'Net CONE'!$G$12:$G$41,0)/(DATE(LEFT($A$1,4)*1+1,5,31)-(DATE(LEFT($A$1,4)*1,6,1))+1) -> 450.15152 | F20: =_xlfn.XLOOKUP("PSEG",'Net CONE'!$A$12:$A$41,'Net CONE'!$G$12:$G$41,0)/(DATE(LEFT($A$1,4)*1+1,5,31)-(DATE(LEFT($A$1,4)*1,6,1))+1) -> 158.68354 | G20: =_xlfn.XLOOKUP("PSEG",'Net CONE'!$A$12:$A$41,'Net CONE'!$G$12:$G$41,0)/(DATE(LEFT($A$1,4)*1+1,5,31)-(DATE(LEFT($A$1,4)*1,6,1))+1) -> 158.68354 | H20: =_xlfn.XLOOKUP("DPL",'Net CONE'!$A$12:$A$41,'Net CONE'!$G$12:$G$41,0)/(DATE(LEFT($A$1,4)*1+1,5,31)-(DATE(LEFT($A$1,4)*1,6,1))+1) -> 334.27848 | I20: =_xlfn.XLOOKUP(I12,'Net CONE'!$A$12:$A$41,'Net CONE'!$G$12:$G$41,0)/(DATE(LEFT($A$1,4)*1+1,5,31)-(DATE(LEFT($A$1,4)*1,6,1))+1) -> 368.81013 | J20: =_xlfn.XLOOKUP(J12,'Net CONE'!$A$12:$A$41,'Net CONE'!$G$12:$G$41,0)/(DATE(LEFT($A$1,4)*1+1,5,31)-(DATE(LEFT($A$1,4)*1,6,1))+1) -> 436.40506 | K20: =_xlfn.XLOOKUP("ATSI",'Net CONE'!$A$12:$A$41,'Net CONE'!$G$12:$G$41,0)/(DATE(LEFT($A$1,4)*1+1,5,31)-(DATE(LEFT($A$1,4)*1,6,1))+1) -> 436.40506 | L20: =_xlfn.XLOOKUP(L12,'Net CONE'!$A$12:$A$41,'Net CONE'!$G$12:$G$41,0)/(DATE(LEFT($A$1,4)*1+1,5,31)-(DATE(LEFT($A$1,4)*1,6,1))+1) -> 283.18987 | M20: =_xlfn.XLOOKUP(M12,'Net CONE'!$A$12:$A$41,'Net CONE'!$G$12:$G$41,0)/(DATE(LEFT($A$1,4)*1+1,5,31)-(DATE(LEFT($A$1,4)*1,6,1))+1) -> 490.21519 | N20: =_xlfn.XLOOKUP("PPL",'Net CONE'!$A$12:$A$41,'Net CONE'!$G$12:$G$41,0)/(DATE(LEFT($A$1,4)*1+1,5,31)-(DATE(LEFT($A$1,4)*1,6,1))+1) -> 265.31646 | O20: =_xlfn.XLOOKUP(O12,'Net CONE'!$A$12:$A$41,'Net CONE'!$G$12:$G$41,0)/(DATE(LEFT($A$1,4)*1+1,5,31)-(DATE(LEFT($A$1,4)*1,6,1))+1) -> 469.16456 | P20: =_xlfn.XLOOKUP(P12,'Net CONE'!$A$12:$A$41,'Net CONE'!$G$12:$G$41,0)/(DATE(LEFT($A$1,4)*1+1,5,31)-(DATE(LEFT($A$1,4)*1,6,1))+1) -> 445.60759 | Q20: =_xlfn.XLOOKUP(Q12,'Net CONE'!$A$12:$A$41,'Net CONE'!$G$12:$G$41,0)/(DATE(LEFT($A$1,4)*1+1,5,31)-(DATE(LEFT($A$1,4)*1,6,1))+1) -> 574.5443 | R20: =_xlfn.XLOOKUP(R12,'Net CONE'!$A$12:$A$41,'Net CONE'!$G$12:$G$41,0)/(DATE(LEFT($A$1,4)*1+1,5,31)-(DATE(LEFT($A$1,4)*1,6,1))+1) -> 163.91139
A21: Variable Resource Requirement Curve:
A22: Point (a) UCAP Price, $/MW-Day | B22: 325 | C22: 325 | D22: 325 | E22: 325 | F22: 325 | G22: 325 | H22: 325 | I22: 325 | J22: 325 | K22: 325 | L22: 325 | M22: 325 | N22: 325 | O22: 325 | P22: 325 | Q22: 325 | R22: 325
A23: Point (b) UCAP Price, $/MW-Day | B23: 277.36 | C23: 312.45 | D23: 175 | E23: 273.89 | F23: 175 | G23: 175 | H23: 309.37 | I23: 304.39 | J23: 265.08 | K23: 265.08 | L23: 175 | M23: 258.86 | N23: 175 | O23: 252.8 | P23: 261.63 | Q23: 213.28 | R23: 175
A24: Point (c) UCAP Price, $/MW-Day | B24: 175 | C24: 175 | D24: 175 | E24: 175 | F24: 175 | G24: 175 | H24: 175 | I24: 175 | J24: 175 | K24: 175 | L24: 175 | M24: 175 | N24: 175 | O24: 175 | P24: 175 | Q24: 175 | R24: 175
A25: Point (d) UCAP Price, $/MW-Day | B25: 175 | C25: 175 | E25: 175 | H25: 175 | I25: 175 | J25: 175 | K25: 175 | M25: 175 | O25: 175 | P25: 175 | Q25: 175
A26: Point (a) UCAP Level, MW | B26: 146703 | C26: 55241.9 | D26: 31810.8 | E26: 13464.7 | F26: 11079.2 | G26: 5340.7 | H26: 2720.8 | I26: 6574.9 | J26: 12661.6 | K26: 5260.7 | L26: 23327 | M26: 7051.4 | N26: 10315.9 | O26: 3821.9 | P26: 5711.7 | Q26: 30072.6 | R26: 6388.5
A27: Point (b) UCAP Level, MW | B27: 147326.3 | C27: 55296.6 | D27: 32405.6 | E27: 13526.9 | F27: 11274.5 | G27: 5434.8 | H27: 2724.2 | I27: 6585.9 | J27: 12732.5 | K27: 5290.2 | L27: 23723.5 | M27: 7096.1 | N27: 10522.9 | O27: 3849 | P27: 5746 | Q27: 30465.7 | R27: 6501.7
A28: Point (c) UCAP Level, MW | B28: 149736.8 | C28: 56375.1 | D28: 33099.5 | E28: 13743.4 | F28: 11502.2 | G28: 5544.5 | H28: 2776.6 | I28: 6710 | J28: 12924.3 | K28: 5369.9 | L28: 24186.2 | M28: 7198 | N28: 10764.3 | O28: 3901.5 | P28: 5830.4 | Q28: 30708.1 | R28: 6633.7
A29: Point (d) UCAP Level, MW | B29: 153858 | C29: 57748.2 | E29: 14126.6 | H29: 2844.9 | I29: 6877.9 | J29: 13297 | K29: 5524.7 | M29: 7410.7 | O29: 4019.6 | P29: 6000.8 | Q29: 31816.4
A30: Nominated PRD Value, MW | B30: =C30+J30+L30+O30+P30 -> 0 | C30: =D30+E30+N30 -> 0 | D30: =0+H30+R30 -> 0 | E30: =I30+M30 -> 0 | F30: 0 | G30: 0 | H30: 0 | I30: 0 | J30: 0 | K30: 0 | L30: 0 | M30: 0 | N30: 0 | O30: 0 | P30: 0 | Q30: 0 | R30: 0
A31: VRR Curve adjusted for PRD:
A32: Point (a1) UCAP Price, $/MW-Day
A33: Point (b1) UCAP Price, $/MW-Day
A34: Point (prd1) UCAP Price, $/MW-Day
A35: Point (prd2) UCAP Price, $/MW-Day
A36: Point (c) UCAP Price, $/MW-Day
A37: Point (a1) UCAP Level, MW
A38: Point (b1) UCAP Level, MW
A39: Point (prd1) UCAP Level, MW
A40: Point (prd2) UCAP Level, MW
A41: Point (c) UCAP Level, MW
A42: Pre-Auction Credit Rate, $/MW | B42: =ROUND(MAX((B19-B20)*0.5, 20)*((DATE(LEFT($A$1,4)*1+1,5,31)-(DATE(LEFT($A$1,4)*1,6,1))+1)),2) -> 59438.77 | C42: =ROUND(MAX((C19-C20)*0.5, 20)*((DATE(LEFT($A$1,4)*1+1,5,31)-(DATE(LEFT($A$1,4)*1,6,1))+1)),2) -> 78409.02 | D42: =ROUND(MAX((D19-D20)*0.5, 20)*((DATE(LEFT($A$1,4)*1+1,5,31)-(DATE(LEFT($A$1,4)*1,6,1))+1)),2) -> 98870.92 | E42: =ROUND(MAX((E19-E20)*0.5, 20)*((DATE(LEFT($A$1,4)*1+1,5,31)-(DATE(LEFT($A$1,4)*1,6,1))+1)),2) -> 58354.1 | F42: =ROUND(MAX((F19-F20)*0.5, 20)*((DATE(LEFT($A$1,4)*1+1,5,31)-(DATE(LEFT($A$1,4)*1,6,1))+1)),2) -> 109015.73 | G42: =ROUND(MAX((G19-G20)*0.5, 20)*((DATE(LEFT($A$1,4)*1+1,5,31)-(DATE(LEFT($A$1,4)*1,6,1))+1)),2) -> 109015.73 | H42: =ROUND(MAX((H19-H20)*0.5, 20)*((DATE(LEFT($A$1,4)*1+1,5,31)-(DATE(LEFT($A$1,4)*1,6,1))+1)),2) -> 76969.65 | I42: =ROUND(MAX((I19-I20)*0.5, 20)*((DATE(LEFT($A$1,4)*1+1,5,31)-(DATE(LEFT($A$1,4)*1,6,1))+1)),2) -> 73198.9 | ... R42: =ROUND(MAX((R19-R20)*0.5, 20)*((DATE(LEFT($A$1,4)*1+1,5,31)-(DATE(LEFT($A$1,4)*1,6,1))+1)),2) -> 108061.65
A43: Post-Auction Credit Rate, $/MW | B43: 23725 | C43: 67204.384 | D43: 98870.923 | E43: 23725 | F43: 109015.73 | G43: 109015.73 | H43: 63793.076 | I43: 54856.397 | J43: 23725 | K43: 23725 | L43: 105280.62 | M43: 23725 | N43: 88288.672 | O43: 23725 | P43: 23725 | Q43: 23725 | R43: 108061.65
A44: Please see 28/29 BRA Auction Results file (BRA ICTRs tab) for data on awarded Participant-Funded ICTRs
A45: FRR Load Requirement (% Obligation):
A46: Minimum Internal Resource Requirement | B46: NA | C46: =MIN(ROUND((C15-C14)/(I79*$B$7),3),100%) -> 1 | D46: =ROUND((D15-D14)/(I76*$B$7),3) -> 0.858 | E46: =ROUND((E15-E14)/(I77*$B$7),3) -> 0.666 | F46: NA | G46: NA | H46: NA | I46: NA | J46: NA | K46: NA | L46: NA | M46: =ROUND((M15-M14)/(I57*$B$7),3) -> 0.23 | N46: NA | O46: NA | P46: NA | Q46: =ROUND((Q15-Q14)/(I62*$B$7),3) -> 0.912 | R46: NA
A47: * - Participant Funded ICTRs will be updated on final Planning Parameters posting after the completion of the 28/29 BRA
A49: LDA CETO/CETL Data; Zonal Peak Loads, Base Zonal FRR Scaling Factors, and FRR load.
A50: LDA/Zone | B50: CETO (Capacity Emergency Transfer Objective) | C50: CETL (Capacity Emergency Transfer Limit) | D50: CETL to CETO Ratio % | E50: 2025 Zonal W/N Coincident Peak Loads | F50: LA Adder** | G50: Preliminary Zonal Peak Load Forecast minus LA Adder | H50: Base Zonal FRR Scaling Factor | I50: Preliminary Zonal Peak Load Forecast | J50: FRR Portion of the Preliminary Peak Load Forecast | K50: Preliminary Zonal Peak Load Forecast minus FRR Load | L50: LDA/Zone
A51: RTO | B51: NA | C51: NA | D51: NA | E51: =E52+E53+E54+E55+E57+E58+E59+E60+E61+E62+E63+E65+E66+E67+E68+E69+E70+E71+E72+E73+E75 -> 153870 | F51: =F52+F53+F54+F55+F57+F58+F59+F60+F61+F62+F63+F65+F66+F67+F68+F69+F70+F71+F72+F73+F75 -> 16252 | G51: =G52+G53+G54+G55+G57+G58+G59+G60+G61+G62+G63+G65+G66+G67+G68+G69+G70+G71+G72+G73+G75 -> 149701.5 | H51: NA | I51: =I52+I53+I54+I55+I57+I58+I59+I60+I61+I62+I63+I65+I66+I67+I68+I69+I70+I71+I72+I73+I75 -> 165953.5 | J51: =J52+J53+J54+J55+J57+J58+J59+J60+J61+J62+J63+J65+J66+J67+J69+J70+J71+J72+J73+J75 -> 11556 | K51: =K52+K53+K54+K55+K57+K58+K59+K60+K61+K62+K63+K65+K66+K67+K68+K69+K70+K71+K72+K73+K75 -> 154397.5 | L51: RTO
A52: AE | B52: 2221 | C52: >2,554.2 | D52: =IF(IFERROR(SEARCH(">",C52),0),">115%",IF(B52>0,C52/B52,"*")) -> >115% | E52: 2315 | F52: 0 | G52: =I52-F52 -> 2320 | H52: =G52/E52 -> 1.0021598 | I52: 2320 | J52: 0 | K52: =I52-J52 -> 2320 | L52: AE
A53: AEP | B53: 3833 | C53: >4,408.0 | D53: =IF(IFERROR(SEARCH(">",C53),0),">115%",IF(B53>0,C53/B53,"*")) -> >115% | E53: 22985 | F53: 4748 | G53: =I53-F53 -> 22249 | H53: =G53/E53 -> 0.96797912 | I53: 26997 | J53: 11556 | K53: =I53-J53 -> 15441 | L53: AEP
A54: APS | B54: 1601 | C54: >1,841.2 | D54: =IF(IFERROR(SEARCH(">",C54),0),">115%",IF(B54>0,C54/B54,"*")) -> >115% | E54: 8600 | F54: 319 | G54: =I54-F54 -> 8513 | H54: =G54/E54 -> 0.98988372 | I54: 8832 | J54: 0 | K54: =I54-J54 -> 8832 | L54: APS
A55: ATSI | B55: 3910 | C55: >11803 | D55: =IF(IFERROR(SEARCH(">",C55),0),">115%",IF(B55>0,C55/B55,"*")) -> >115% | E55: 12390 | F55: 299 | G55: =I55-F55 -> 12112 | H55: =G55/E55 -> 0.97756255 | I55: 12411 | J55: 0 | K55: =I55-J55 -> 12411 | L55: ATSI
A56: ATSI-CLEVELAND | B56: 3534 | C56: 5430 | D56: =IF(IFERROR(SEARCH(">",C56),0),">115%",IF(B56>0,C56/B56,"*")) -> 1.5365025 | E56: NA | F56: 0 | G56: =I56-F56 -> 4046 | H56: NA | I56: 4046 | J56: 0 | K56: =I56-J56 -> 4046 | L56: ATSI-CLEVELAND
A57: BGE | B57: 4568 | C57: 5658 | D57: =IF(IFERROR(SEARCH(">",C57),0),">115%",IF(B57>0,C57/B57,"*")) -> 1.2386165 | E57: 6320 | F57: 43 | G57: =I57-F57 -> 6117 | H57: =G57/E57 -> 0.96787975 | I57: 6160 | J57: 0 | K57: =I57-J57 -> 6160 | L57: BGE
A58: COMED | B58: 1267 | C58: 1586 | D58: =IF(IFERROR(SEARCH(">",C58),0),">115%",IF(B58>0,C58/B58,"*")) -> 1.2517758 | E58: 19090 | F58: 1663 | G58: =I58-F58 -> 18478 | H58: =G58/E58 -> 0.96794133 | I58: 20141 | J58: 0 | K58: =I58-J58 -> 20141 | L58: COMED
A59: DAYTON | B59: 2785 | C59: 4432 | D59: =IF(IFERROR(SEARCH(">",C59),0),">115%",IF(B59>0,C59/B59,"*")) -> 1.5913824 | E59: 3150 | F59: 277 | G59: =I59-F59 -> 3134 | H59: =G59/E59 -> 0.99492063 | I59: 3411 | J59: 0 | K59: =I59-J59 -> 3411 | L59: DAYTON
A60: DEOK | B60: 2800 | C60: 5934 | D60: =IF(IFERROR(SEARCH(">",C60),0),">115%",IF(B60>0,C60/B60,"*")) -> 2.1192857 | E60: 5070 | F60: 0 | G60: =I60-F60 -> 5087 | H60: =G60/E60 -> 1.0033531 | I60: 5087 | J60: 0 | K60: =I60-J60 -> 5087 | L60: DEOK
A61: DLCO | B61: 1828 | C61: >2,102.2 | D61: =IF(IFERROR(SEARCH(">",C61),0),">115%",IF(B61>0,C61/B61,"*")) -> >115% | E61: 2610 | F61: 0 | G61: =I61-F61 -> 2586 | H61: =G61/E61 -> 0.9908046 | I61: 2586 | J61: 0 | K61: =I61-J61 -> 2586 | L61: DLCO
A62: DOM | B62: 7758 | C62: 5992 | D62: =IF(IFERROR(SEARCH(">",C62),0),">115%",IF(B62>0,C62/B62,"*")) -> 0.77236401 | E62: 22700 | F62: 6956 | G62: =I62-F62 -> 21067 | H62: =G62/E62 -> 0.92806167 | I62: 28023 | J62: 0 | K62: =I62-J62 -> 28023 | L62: DOM
A63: DPL | B63: 1476 | C63: >1,697.4 | D63: =IF(IFERROR(SEARCH(">",C63),0),">115%",IF(B63>0,C63/B63,"*")) -> >115% | E63: 3770 | F63: 0 | G63: =I63-F63 -> 3748 | H63: =G63/E63 -> 0.99416446 | I63: 3748 | J63: 0 | K63: =I63-J63 -> 3748 | L63: DPL
A64: DPL SOUTH | B64: 1654 | C64: 2005 | D64: =IF(IFERROR(SEARCH(">",C64),0),">115%",IF(B64>0,C64/B64,"*")) -> 1.2122128 | E64: NA | F64: 0 | G64: =I64-F64 -> 2331.3 | H64: NA | I64: 2331.3 | J64: 0 | K64: =I64-J64 -> 2331.3 | L64: DPL SOUTH
A65: EKPC | B65: 959 | C65: >1,102.9 | D65: =IF(IFERROR(SEARCH(">",C65),0),">115%",IF(B65>0,C65/B65,"*")) -> >115% | E65: 2010 | F65: 0 | G65: =I65-F65 -> 2421.5 | H65: =G65/E65 -> 1.2047264 | I65: 2421.5 | J65: 0 | K65: =I65-J65 -> 2421.5 | L65: EKPC
A66: JCPL | B66: 3628 | C66: 5312 | D66: =IF(IFERROR(SEARCH(">",C66),0),">115%",IF(B66>0,C66/B66,"*")) -> 1.4641676 | E66: 5760 | F66: 0 | G66: =I66-F66 -> 5674 | H66: =G66/E66 -> 0.98506944 | I66: 5674 | J66: 0 | K66: =I66-J66 -> 5674 | L66: JCPL
A67: METED | B67: 1481 | C67: >1,703.2 | D67: =IF(IFERROR(SEARCH(">",C67),0),">115%",IF(B67>0,C67/B67,"*")) -> >115% | E67: 2940 | F67: 0 | G67: =I67-F67 -> 2916 | H67: =G67/E67 -> 0.99183673 | I67: 2916 | J67: 0 | K67: =I67-J67 -> 2916 | L67: METED
A68: OVEC | B68: NA | C68: NA | D68: NA | E68: 60 | F68: 0 | G68: =I68-F68 -> 60 | H68: =G68/E68 -> 1 | I68: 60 | J68: 0 | K68: =I68-J68 -> 60 | L68: OVEC
A69: PECO | B69: 3016 | C69: >3,468.4 | D69: =IF(IFERROR(SEARCH(">",C69),0),">115%",IF(B69>0,C69/B69,"*")) -> >115% | E69: 8120 | F69: 281 | G69: =I69-F69 -> 7984 | H69: =G69/E69 -> 0.98325123 | I69: 8265 | J69: 0 | K69: =I69-J69 -> 8265 | L69: PECO
A70: PENLC | B70: 232 | C70: >266.8 | D70: =IF(IFERROR(SEARCH(">",C70),0),">115%",IF(B70>0,C70/B70,"*")) -> >115% | E70: 2770 | F70: 0 | G70: =I70-F70 -> 2664 | H70: =G70/E70 -> 0.96173285 | I70: 2664 | J70: 0 | K70: =I70-J70 -> 2664 | L70: PENLC
A71: PEPCO | B71: 3888 | C71: 5770 | D71: =IF(IFERROR(SEARCH(">",C71),0),">115%",IF(B71>0,C71/B71,"*")) -> 1.4840535 | E71: 5830 | F71: 0 | G71: =I71-F71 -> 5758 | H71: =G71/E71 -> 0.98765009 | I71: 5758 | J71: 0 | K71: =I71-J71 -> 5758 | L71: PEPCO
A72: PL (incl. UGI) | B72: 1187 | C72: 5312 | D72: =IF(IFERROR(SEARCH(">",C72),0),">115%",IF(B72>0,C72/B72,"*")) -> 4.4751474 | E72: 7220 | F72: 1274 | G72: =I72-F72 -> 7074 | H72: =G72/E72 -> 0.97977839 | I72: 8348 | J72: 0 | K72: =I72-J72 -> 8348 | L72: PL (incl. UGI)
A73: PS | B73: 6481 | C73: 8873 | D73: =IF(IFERROR(SEARCH(">",C73),0),">115%",IF(B73>0,C73/B73,"*")) -> 1.3690788 | E73: 9770 | F73: 392 | G73: =I73-F73 -> 9363 | H73: =G73/E73 -> 0.95834186 | I73: 9755 | J73: 0 | K73: =I73-J73 -> 9755 | L73: PS
A74: PS NORTH | B74: 2712 | C74: 4656 | D74: =IF(IFERROR(SEARCH(">",C74),0),">115%",IF(B74>0,C74/B74,"*")) -> 1.7168142 | E74: NA | F74: 0 | G74: =I74-F74 -> 4721.4 | H74: NA | I74: 4721.4 | J74: 0 | K74: =I74-J74 -> 4721.4 | L74: PS NORTH
A75: RECO | B75: NA | C75: NA | D75: NA | E75: 390 | F75: 0 | G75: =I75-F75 -> 376 | H75: =G75/E75 -> 0.96410256 | I75: 376 | J75: 0 | K75: =I75-J75 -> 376 | L75: RECO
A76: EMAAC | B76: 5903 | C76: 6904 | D76: =IF(IFERROR(SEARCH(">",C76),0),">115%",IF(B76>0,C76/B76,"*")) -> 1.1695748 | I76: 30138 | J76: =J52+J63+J66+J69+J73+J75 -> 0 | L76: EMAAC
A77: SWMAAC | B77: 6131 | C77: 5862 | D77: =IF(IFERROR(SEARCH(">",C77),0),">115%",IF(B77>0,C77/B77,"*")) -> 0.95612461 | I77: 11918 | J77: =J57+J71 -> 0 | L77: SWMAAC
A78: Western MAAC | B78: -6515 | C78: * | D78: * | I78: 13928 | J78: =J67+J70+J72 -> 0 | L78: Western MAAC
A79: MAAC | B79: -187 | C79: 1318 | D79: * | I79: 55984 | J79: =J76+J77+J78 -> 0 | L79: MAAC
A80: Western PJM | B80: 6197 | C80: *** | D80: >115%*** | I80: 81946.5 | J80: =J53+J54+J55+J58+J59+J60+J61+J65 -> 11556 | L80: Western PJM
A81: * LDA has adequate internal resources to meet the reliability criterion.
A82: ** LA Adder represents Load Adjustments in auction DY for each zone. See M19 Attachment B.
A83: *** Analysis assumes sufficient resources outside the LDA under study
A85: Limiting conditions at the CETL for modeled LDAs:
A86: LDA | B86: Violation | D86: Limiting Facility
A87: MAAC | B87: Discreet Thermal | D87: Morrisville - Loudoun 500 kV line for the loss of Brister - Ox 500 kV line
A88: EMAAC | B88: Mean Thermal | D88: Morrisville - Loudoun 500 kV line for the loss of Brister - Ox 500 kV line Elroy - Hosensack 500 kV for the loss of Alburtis - Branchburg 500 kV
A89: SWMAAC | B89: Discrete Voltage | D89: Voltage collapse for the loss of Brighton - Conastone 500 kV line (5011)
A90: PS | B90: Mean Thermal | D90: Morrisville - Loudoun 500 kV line for the loss of Brister - Ox 500 kV line Laurel Ave - Livingston 230 kV for the loss of Roseland - West Orange 230 kV Roseland _Wilpipe 230 kV for the loss of Rosland - Cedar Grove 230 kV
A91: PSNORTH | B91: Discrete Thermal | D91: Morrisville - Loudoun 500 kV line for the loss of Brister - Ox 500 kV line Laurel Ave - Livingston 230 kV for the loss of Roseland - West Orange 230 kV Roseland _Wilpipe 230 kV for the loss of Rosland - Cedar Grove 230 k
A92: DPLSOUTH | B92: Discrete Thermal | D92: Loudoun - Morrisville 500 kV line for the loss of Brister - Ox 500 kV line Cool Springs - Miford 230 kV for the loss of Milford - Indian River 230 kV line
A93: PEPCO | B93: Mean/Discrete Thermal | D93: Morrisville - Loudoun 500 kV line for the loss of Brister - Ox 500 kV line
A94: ATSI | B94: Mean Thermal | D94: No limiting facility found
A95: ATSI-CLEVELAND | B95: Mean/Discrete Voltage | D95: Low voltage at Lake Ave, Avon and Beaver 345 kV substations for the loss of Beaver - AC2-103 Tap (to Davis -Besse) 345 kV line
A96: COMED | B96: Discrete Thermal | D96: Goodings Grove - Lockport "B" 345 kV line for the loss of Lockport - Kendall County Ec 345kv
A97: BGE | B97: Discrete Voltage | D97: Voltage collapse for the loss of Brighton - Conastone 500 kV line (5011)
... A102: JCPL | B102: Mean Thermal | D102: Morrisville - Loudoun 500 kV line for the loss of Brister - Ox 500 kV line Cookstown - Lumberton 230 kV for the loss of Larrabee - Smithburg 230 kV Middlesex - Lake Nelson (I) 230 kV for the loss of Larrabee - Smithburg 230 kV
A103: 3/20/2026 - Initial posting - please note that resources with Reliability Must Run requirements are included in the Planning Parameters modeling.
A104: 4/21/2026 - Updated Limiting Facility for COMED LDA.
A105: 4/29/2026 - Added VRR Curve to reflect FERC approval of the extension of cap and floor. Added final FRR data.
A106: 7/27/2026 - Added Post-Auction Credit Rate data

Sheet Net CONE
A1: RPM CONE and E&AS Values for 2028/2029 Base Residual Auction
A2: ICAP to UCAP Conversion Factor:
A3: UCAP Price = ICAP Price / Pool-Wide Average Accredited UCAP Factor
A4: Reference Resource Accredited UCAP Factor | H4: 0.79
A5: CONE Area 1: AE, DPL, JCPL, PECO, PS, RECO
A6: CONE Area 2: BGE, PEPCO
A7: CONE Area 3: AEP, APS, ATSI, Dayton, DEOK, Dominion, Duquesne (DLCo), EKPC, OVEC
A8: CONE Area 4: MetEd, Penelec, PPL
A9: CONE Area 5: ComEd
A11: Zone/LDA | B11: 2028/2029 BRA CONE: Levelized Revenue Requirement, $/MW-Year * | C11: Escalation | D11: 2028/2029 BRA CONE: Levelized Revenue Requirement, $/MW-Year | E11: Gross CONE, $/MW-Day, UCAP Price | F11: Forward Net E&AS Revenue Offset, $/MW-Year, ICAP | G11: Forward Net E&AS Revenue Offset, $/MW-Year, UCAP | H11: Net CONE, $/MW-Day, ICAP Price | I11: Net CONE, $/MW-Day, UCAP Price | J11: LDA Modeled with VRR Curve
A12: CONE Area 1 | B12: 218000 | C12: 1 | D12: =B12*C12 -> 218000 | E12: =ROUND(D12/(((DATE(LEFT('Planning Parameters'!$A$1,4)*1+1,5,31)-(DATE(LEFT('Planning Parameters'!$A$1,4)*1,6,1))+1))*$H$4),2) -> 756.03
A13: AE | E13: =$E$12 -> 756.03 | F13: 49275 | G13: =F13/$H$4 -> 62373.418 | H13: =MAX(($D$12-F13)/((DATE(LEFT('Planning Parameters'!$A$1,4)*1+1,5,31)-(DATE(LEFT('Planning Parameters'!$A$1,4)*1,6,1))+1)),0) -> 462.26027 | I13: =MAX(ROUND(H13/$H$4,2),0) -> 585.14
A14: DPL | E14: =$E$12 -> 756.03 | F14: 96389.2 | G14: =F14/$H$4 -> 122011.65 | H14: =MAX(($D$12-F14)/((DATE(LEFT('Planning Parameters'!$A$1,4)*1+1,5,31)-(DATE(LEFT('Planning Parameters'!$A$1,4)*1,6,1))+1)),0) -> 333.18027 | I14: =MAX(ROUND(H14/$H$4,2),0) -> 421.75 | J14: DPL SOUTH
A15: JCPL | E15: =$E$12 -> 756.03 | F15: 47263.85 | G15: =F15/$H$4 -> 59827.658 | H15: =MAX(($D$12-F15)/((DATE(LEFT('Planning Parameters'!$A$1,4)*1+1,5,31)-(DATE(LEFT('Planning Parameters'!$A$1,4)*1,6,1))+1)),0) -> 467.77027 | I15: =MAX(ROUND(H15/$H$4,2),0) -> 592.11 | J15: JCPL
A16: PE | E16: =$E$12 -> 756.03 | F16: 76368.95 | G16: =F16/$H$4 -> 96669.557 | H16: =MAX(($D$12-F16)/((DATE(LEFT('Planning Parameters'!$A$1,4)*1+1,5,31)-(DATE(LEFT('Planning Parameters'!$A$1,4)*1,6,1))+1)),0) -> 388.03027 | I16: =MAX(ROUND(H16/$H$4,2),0) -> 491.18
A17: PSEG | E17: =$E$12 -> 756.03 | F17: 45756.4 | G17: =F17/$H$4 -> 57919.494 | H17: =MAX(($D$12-F17)/((DATE(LEFT('Planning Parameters'!$A$1,4)*1+1,5,31)-(DATE(LEFT('Planning Parameters'!$A$1,4)*1,6,1))+1)),0) -> 471.90027 | I17: =MAX(ROUND(H17/$H$4,2),0) -> 597.34 | J17: PS, PSEG NORTH
A18: RECO | E18: =$E$12 -> 756.03 | F18: 53932.4 | G18: =F18/$H$4 -> 68268.861 | H18: =MAX(($D$12-F18)/((DATE(LEFT('Planning Parameters'!$A$1,4)*1+1,5,31)-(DATE(LEFT('Planning Parameters'!$A$1,4)*1,6,1))+1)),0) -> 449.50027 | I18: =MAX(ROUND(H18/$H$4,2),0) -> 568.99
A19: EMAAC | E19: =$E$12 -> 756.03 | F19: =_xlfn.PERCENTILE.INC(F13:F18,0.67) -> 61785.192 | G19: =_xlfn.PERCENTILE.INC(G13:G18,0.67) -> 78209.104 | H19: =MAX(($D$12-F19)/((DATE(LEFT('Planning Parameters'!$A$1,4)*1+1,5,31)-(DATE(LEFT('Planning Parameters'!$A$1,4)*1,6,1))+1)),0) -> 427.98577 | I19: =MAX(ROUND(H19/$H$4,2),0) -> 541.75 | J19: EMAAC
A20: CONE Area 2 | B20: 222000 | C20: 1 | D20: =B20*C20 -> 222000 | E20: =ROUND(D20/(((DATE(LEFT('Planning Parameters'!$A$1,4)*1+1,5,31)-(DATE(LEFT('Planning Parameters'!$A$1,4)*1,6,1))+1))*$H$4),2) -> 769.9
A21: BGE | E21: =$E$20 -> 769.9 | F21: 141353.55 | G21: =F21/$H$4 -> 178928.54 | H21: =MAX(($D$20-F21)/((DATE(LEFT('Planning Parameters'!$A$1,4)*1+1,5,31)-(DATE(LEFT('Planning Parameters'!$A$1,4)*1,6,1))+1)),0) -> 220.94918 | I21: =MAX(ROUND(H21/$H$4,2),0) -> 279.68 | J21: BGE
A22: PEPCO | E22: =$E$20 -> 769.9 | F22: 106346.4 | G22: =F22/$H$4 -> 134615.7 | H22: =MAX(($D$20-F22)/((DATE(LEFT('Planning Parameters'!$A$1,4)*1+1,5,31)-(DATE(LEFT('Planning Parameters'!$A$1,4)*1,6,1))+1)),0) -> 316.85918 | I22: =MAX(ROUND(H22/$H$4,2),0) -> 401.09 | J22: PEPCO
A23: SWMAAC | E23: =$E$20 -> 769.9 | F23: =_xlfn.PERCENTILE.INC(F21:F22,0.67) -> 129801.19 | G23: =_xlfn.PERCENTILE.INC(G21:G22,0.67) -> 164305.3 | H23: =MAX(($D$20-F23)/((DATE(LEFT('Planning Parameters'!$A$1,4)*1+1,5,31)-(DATE(LEFT('Planning Parameters'!$A$1,4)*1,6,1))+1)),0) -> 252.59948 | I23: =MAX(ROUND(H23/$H$4,2),0) -> 319.75 | J23: SWMAAC
A24: CONE Area 4 | B24: 216000 | C24: 1 | D24: =B24*C24 -> 216000 | E24: =ROUND(D24/(((DATE(LEFT('Planning Parameters'!$A$1,4)*1+1,5,31)-(DATE(LEFT('Planning Parameters'!$A$1,4)*1,6,1))+1))*$H$4),2) -> 749.09
A25: METED | E25: =$E$24 -> 749.09 | F25: 89414.05 | G25: =F25/$H$4 -> 113182.34 | H25: =MAX(($D$24-F25)/((DATE(LEFT('Planning Parameters'!$A$1,4)*1+1,5,31)-(DATE(LEFT('Planning Parameters'!$A$1,4)*1,6,1))+1)),0) -> 346.81082 | I25: =MAX(ROUND(H25/$H$4,2),0) -> 439
A26: PENELEC | E26: =$E$24 -> 749.09 | F26: 136396.85 | G26: =F26/$H$4 -> 172654.24 | H26: =MAX(($D$24-F26)/((DATE(LEFT('Planning Parameters'!$A$1,4)*1+1,5,31)-(DATE(LEFT('Planning Parameters'!$A$1,4)*1,6,1))+1)),0) -> 218.09082 | I26: =MAX(ROUND(H26/$H$4,2),0) -> 276.06
A27: PPL | E27: =$E$24 -> 749.09 | F27: 76504 | G27: =F27/$H$4 -> 96840.506 | H27: =MAX(($D$24-F27)/((DATE(LEFT('Planning Parameters'!$A$1,4)*1+1,5,31)-(DATE(LEFT('Planning Parameters'!$A$1,4)*1,6,1))+1)),0) -> 382.18082 | I27: =MAX(ROUND(H27/$H$4,2),0) -> 483.77 | J27: PPL
A28: MAAC | E28: =ROUND(AVERAGE(E13,E14,E15,E16,E17,E18,E21,E22,E25,E26,E27),2) -> 756.66 | F28: =_xlfn.PERCENTILE.INC((F25:F27,F21:F22,F13:F18),0.67) -> 94296.655 | G28: =_xlfn.PERCENTILE.INC((G25:G27,G21:G22,G13:G18),0.67) -> 119362.85 | H28: =MAX(($D$24-F28)/((DATE(LEFT('Planning Parameters'!$A$1,4)*1+1,5,31)-(DATE(LEFT('Planning Parameters'!$A$1,4)*1,6,1))+1)),0) -> 333.43382 | I28: =MAX(ROUND(H28/$H$4,2),0) -> 422.07 | J28: MAAC
A29: CONE Area 3 | B29: 215000 | C29: 1 | D29: =B29*C29 -> 215000 | E29: =ROUND(D29/(((DATE(LEFT('Planning Parameters'!$A$1,4)*1+1,5,31)-(DATE(LEFT('Planning Parameters'!$A$1,4)*1,6,1))+1))*$H$4),2) -> 745.62
A30: AEP | E30: =$E$29 -> 745.62 | F30: 131980.35 | G30: =F30/$H$4 -> 167063.73 | H30: =MAX(($D$29-F30)/((DATE(LEFT('Planning Parameters'!$A$1,4)*1+1,5,31)-(DATE(LEFT('Planning Parameters'!$A$1,4)*1,6,1))+1)),0) -> 227.4511 | I30: =MAX(ROUND(H30/$H$4,2),0) -> 287.91
A31: APS | E31: =$E$29 -> 745.62 | F31: 144810.1 | G31: =F31/$H$4 -> 183303.92 | H31: =MAX(($D$29-F31)/((DATE(LEFT('Planning Parameters'!$A$1,4)*1+1,5,31)-(DATE(LEFT('Planning Parameters'!$A$1,4)*1,6,1))+1)),0) -> 192.3011 | I31: =MAX(ROUND(H31/$H$4,2),0) -> 243.42
A32: ATSI | E32: =$E$29 -> 745.62 | F32: 125837.4 | G32: =F32/$H$4 -> 159287.85 | H32: =MAX(($D$29-F32)/((DATE(LEFT('Planning Parameters'!$A$1,4)*1+1,5,31)-(DATE(LEFT('Planning Parameters'!$A$1,4)*1,6,1))+1)),0) -> 244.2811 | I32: =MAX(ROUND(H32/$H$4,2),0) -> 309.22 | J32: ATSI, ATSI CLEVELAND
A33: DAYTON | E33: =$E$29 -> 745.62 | F33: 135283.6 | G33: =F33/$H$4 -> 171245.06 | H33: =MAX(($D$29-F33)/((DATE(LEFT('Planning Parameters'!$A$1,4)*1+1,5,31)-(DATE(LEFT('Planning Parameters'!$A$1,4)*1,6,1))+1)),0) -> 218.4011 | I33: =MAX(ROUND(H33/$H$4,2),0) -> 276.46 | J33: DAYTON
A34: DEOK | E34: =$E$29 -> 745.62 | F34: 128490.95 | G34: =F34/$H$4 -> 162646.77 | H34: =MAX(($D$29-F34)/((DATE(LEFT('Planning Parameters'!$A$1,4)*1+1,5,31)-(DATE(LEFT('Planning Parameters'!$A$1,4)*1,6,1))+1)),0) -> 237.0111 | I34: =MAX(ROUND(H34/$H$4,2),0) -> 300.01 | J34: DEOK
A35: DLCO | E35: =$E$29 -> 745.62 | F35: 104003.1 | G35: =F35/$H$4 -> 131649.49 | H35: =MAX(($D$29-F35)/((DATE(LEFT('Planning Parameters'!$A$1,4)*1+1,5,31)-(DATE(LEFT('Planning Parameters'!$A$1,4)*1,6,1))+1)),0) -> 304.1011 | I35: =MAX(ROUND(H35/$H$4,2),0) -> 384.94
A36: DOM | E36: =$E$29 -> 745.62 | F36: 165669.85 | G36: =F36/$H$4 -> 209708.67 | H36: =MAX(($D$29-F36)/((DATE(LEFT('Planning Parameters'!$A$1,4)*1+1,5,31)-(DATE(LEFT('Planning Parameters'!$A$1,4)*1,6,1))+1)),0) -> 135.1511 | I36: =MAX(ROUND(H36/$H$4,2),0) -> 171.08 | J36: DOM
A37: EKPC | E37: =$E$29 -> 745.62 | F37: 142174.8 | G37: =F37/$H$4 -> 179968.1 | H37: =MAX(($D$29-F37)/((DATE(LEFT('Planning Parameters'!$A$1,4)*1+1,5,31)-(DATE(LEFT('Planning Parameters'!$A$1,4)*1,6,1))+1)),0) -> 199.5211 | I37: =MAX(ROUND(H37/$H$4,2),0) -> 252.56
A38: OVEC | E38: =$E$29 -> 745.62 | F38: 120490.15 | G38: =F38/$H$4 -> 152519.18 | H38: =MAX(($D$29-F38)/((DATE(LEFT('Planning Parameters'!$A$1,4)*1+1,5,31)-(DATE(LEFT('Planning Parameters'!$A$1,4)*1,6,1))+1)),0) -> 258.9311 | I38: =MAX(ROUND(H38/$H$4,2),0) -> 327.76
A39: CONE Area 5 | B39: 248000 | C39: NA | D39: =B39 -> 248000 | E39: =ROUND(D39/(((DATE(LEFT('Planning Parameters'!$A$1,4)*1+1,5,31)-(DATE(LEFT('Planning Parameters'!$A$1,4)*1,6,1))+1))*$H$4),2) -> 860.07
A40: COMED | E40: =E39 -> 860.07 | F40: 81657.8 | G40: =F40/$H$4 -> 103364.3 | H40: =MAX(($D$39-F40)/((DATE(LEFT('Planning Parameters'!$A$1,4)*1+1,5,31)-(DATE(LEFT('Planning Parameters'!$A$1,4)*1,6,1))+1)),0) -> 455.73205 | I40: =MAX(ROUND(H40/$H$4,2),0) -> 576.88 | J40: COMED
A41: RTO | B41: =AVERAGE(B12,B20,B24,B29,B39) -> 223800 | D41: =AVERAGE(D12,D20,D24,D29,D39) -> 223800 | E41: =ROUND(D41/(((DATE(LEFT('Planning Parameters'!$A$1,4)*1+1,5,31)-(DATE(LEFT('Planning Parameters'!$A$1,4)*1,6,1))+1))*$H$4),2) -> 776.14 | F41: =_xlfn.PERCENTILE.INC((F40,F30:F38,F25:F27,F21:F22,F13:F18),0.67) -> 129886.71 | G41: =_xlfn.PERCENTILE.INC((G40,G30:G38,G25:G27,G21:G22,G13:G18),0.67) -> 164413.56 | H41: =MAX(($D$41-F41)/((DATE(LEFT('Planning Parameters'!$A$1,4)*1+1,5,31)-(DATE(LEFT('Planning Parameters'!$A$1,4)*1,6,1))+1)),0) -> 257.29668 | I41: =MAX(ROUND(H41/$H$4,2),0) -> 325.69 | J41: RTO
A44: CONE Area 5 29/30, 30/31, and 30/32 includes asset life factor of 1.025, 1.054, and 1.088 respectively.
A45: * The 2028/2029 BRA CONE values are based on PJM’s filing (Docket No. ER26-455) which was FERC approved on January 21, 2026.

Sheet Key Transmission Upgrades
B1: New Key Transmission Upgrades included for 2028/2029 model
A2: UpgradeId | B2: Description | C2: Transmission Owner
A3: b3800.200 | B3: Build a new 500kV line from Aspen - Golden on 500/230kV double circuit structures with substation upgrades at Aspen and Golden. New conductor to have a minimum summer normal rating of 4357MVA. | C3: Dominion
A4: b3800.212 | B4: Build a new 500kV Line from Mars-Golden on 500/230kV double circuit structures with substation upgrades at Golden and Mars. New conductor to have a monimum summer normal rating of 4357 MVA. | C4: Dominion
A5: b3800.213 | B5: Cut 500kV Line # 558 Brambleton - Goose Creek into Aspen substation. Upgrade 500kV terminal equipment at Aspen and Goose Creek to 5000A continuous rating current. At Goose Creek, replace circuit breakers 59582 and 55882, and associated disconnect switches, breaker leads, bus, and line risers to accommodate 5000A rating. | C5: Dominion
A6: b3800.214 | B6: Build a new 500kV Line from Aspen - Goose Creek to achieve a summer rating of 4357 MVA. Install new 500kV terminal equipment at Aspen. | C6: Dominion
A7: b3800.225 | B7: Change 500kV Line #558 destination at Brambleton to Aspen Substation and upgrade line protection relays | C7: Dominion
A8: b3800.311 | B8: Rebuild 500kV Line #545 Bristers - Morrisville as a single circuit monopole line to accommodate the new 500 kV line in the existing ROW. New conductor to have a summer rating of 4357 MVA. | C8: Dominion
A9: b3800.336 | B9: Upgrade and install equipment at Bristers substation to support the new conductor 5000A rating for 500kV Line #545. | C9: Dominion
A10: b4000.343 | B10: Uprate bus at Brambleton to support 500kV Line #558 (Aspen to Brambleton) uprate. | C10: Dominion
A11: n8485.1 | B11: Build a three breaker AE2-051 500 kV switching substation. | C11: Dominion
A12: n8485.2 | B12: Re-arrange line #562 to loop into and out of the new three breaker AE2-051 500 kV switching station | C12: Dominion
A13: b3737.30 | B13: Add third Smithburg 500/230 kV transformer. | C13: JCPL
A15: Key Transmission Upgrades included for 2027/2028 model but not included for 2028/2029 model
A16: Upgrade ID | B16: Description | C16: Transmission Owner
A17: None
